{
  "type": "palladium:compound",
  "layers": [
    {
      "model_layer": "pantheonsent:player#moon_knight_suit",
      "model": "pantheonsent:moon_knight_suit",
      "texture": {
        "base": "pantheonsent:textures/models/moon_knight.png",
        "transformers": [
          {
            "type": "palladium:alpha_mask",
            "mask": "pantheonsent:textures/models/alpha_masks/transformation/transformation_#TIMER.png"
          }
        ],
        "variables": {
          "TIMER": {
            "type": "palladium:ability_integer_property",
            "power": "pantheonsent:moon_knight",
            "ability": "activate",
            "property": "value"
          }
        },
        "output": "pantheonsent:textures/models/armor/moon_knight_#TIMER"
      }
    },
    {
      "model_layer": "pantheonsent:player#moon_knight_suit",
      "model": "pantheonsent:moon_knight_suit",
      "texture": "pantheonsent:textures/models/moon_knight_lights.png",
      "render_type": "glow",
      "conditions": [
        {
          "type": "palladium:ability_integer_property",
          "power": "pantheonsent:moon_knight",
          "ability": "activate",
          "property": "value",
          "min": 1,
          "max": 19
        }
      ]
    }
  ]
}
